[
    {
        "name": "KGF 2",
        "HOCode": "CBF0000009",
        "rating": "U/A"
    },
    {
        "name": "Karnan",
        "HOCode": "CBF0000010",
        "rating": "U/A"
    },
    {
        "name": "Cobra",
        "HOCode": "CBF0000011",
        "rating": "U/A"
    },
    {
        "name": "Maanadu",
        "HOCode": "CBF0000012",
        "rating": "U/A"
    },
    {
        "name": "Doctor",
        "HOCode": "CBF0000013",
        "rating": "U/A"
    },
    {
        "name": "RRR",
        "HOCode": "CBF0000014",
        "rating": "U/A"
    }
]